{"py/object": "rasa.core.featurizers.tracker_featurizers.MaxHistoryTrackerFeaturizer", "state_featurizer": {"py/object": "rasa.core.featurizers.single_state_featurizer.SingleStateFeaturizer", "_default_feature_states": {"intent": {"affirm": 0, "back": 1, "bot_answer": 2, "bot_challenge": 3, "deny": 4, "feelings": 5, "goodbye": 6, "greet": 7, "nlu_fallback": 8, "out_of_scope": 9, "restart": 10, "sergio_accomplishments": 11, "sergio_age": 12, "sergio_born": 13, "sergio_brothers": 14, "sergio_contact": 15, "sergio_contact_link": 16, "sergio_details": 17, "sergio_education_basic": 18, "sergio_from": 19, "sergio_hire": 20, "sergio_hobbies": 21, "sergio_interests": 22, "sergio_lifting": 23, "sergio_pets": 24, "sergio_project_another": 25, "sergio_project_one": 26, "sergio_projects": 27, "sergio_proven": 28, "sergio_work": 29, "session_start": 30, "thanks": 31}, "action_name": {"action_listen": 0, "action_restart": 1, "action_session_start": 2, "action_default_fallback": 3, "action_deactivate_loop": 4, "action_revert_fallback_events": 5, "action_default_ask_affirmation": 6, "action_default_ask_rephrase": 7, "action_two_stage_fallback": 8, "action_unlikely_intent": 9, "action_back": 10, "...": 11, "action_extract_slots": 12, "utter_SergioDegree": 13, "utter_SergioFamily": 14, "utter_SergioFullDetails": 15, "utter_SergioHome": 16, "utter_accomplishments": 17, "utter_bot_explain": 18, "utter_cheer_up": 19, "utter_did_that_help": 20, "utter_goodbye": 21, "utter_greet": 22, "utter_hire": 23, "utter_how_help": 24, "utter_iamabot": 25, "utter_ok": 26, "utter_project_another": 27, "utter_project_one": 28, "utter_prove": 29, "utter_sergio_age": 30, "utter_sergio_born": 31, "utter_sergio_computer_science_interests": 32, "utter_sergio_contact": 33, "utter_sergio_contact_link": 34, "utter_sergio_education_basic": 35, "utter_sergio_family": 36, "utter_sergio_hobbies": 37, "utter_sergio_lifting_maxes": 38, "utter_sergio_pets": 39, "utter_sergio_project": 40, "utter_sergio_work": 41, "utter_sergio_work_full": 42, "utter_thanks": 43}, "entities": {}, "slots": {}, "active_loop": {}}, "action_texts": [], "entity_tag_specs": []}, "max_history": 5, "remove_duplicates": true}